LICENSE
README.rst
pyproject.toml
firebirdsql/__init__.py
firebirdsql/arc4.py
firebirdsql/chacha.py
firebirdsql/consts.py
firebirdsql/decfloat.py
firebirdsql/err.py
firebirdsql/event_conduit.py
firebirdsql/fbcore.py
firebirdsql/fberrmsgs.py
firebirdsql/services.py
firebirdsql/srp.py
firebirdsql/stream.py
firebirdsql/tz_map.py
firebirdsql/tz_utils.py
firebirdsql/utils.py
firebirdsql/wireprotocol.py
firebirdsql/xsqlvar.py
firebirdsql.egg-info/PKG-INFO
firebirdsql.egg-info/SOURCES.txt
firebirdsql.egg-info/dependency_links.txt
firebirdsql.egg-info/top_level.txt
firebirdsql/aio/__init__.py
firebirdsql/aio/context.py
firebirdsql/aio/fbcore.py
firebirdsql/aio/pool.py
firebirdsql/aio/stream.py
firebirdsql/tests/__init__.py
firebirdsql/tests/base.py
firebirdsql/tests/test_arc4.py
firebirdsql/tests/test_async.py
firebirdsql/tests/test_auth.py
firebirdsql/tests/test_backup.py
firebirdsql/tests/test_basic.py
firebirdsql/tests/test_chacha.py
firebirdsql/tests/test_event.py
firebirdsql/tests/test_issues.py
firebirdsql/tests/test_proc.py
firebirdsql/tests/test_services.py
firebirdsql/tests/test_srp.py
firebirdsql/tests/test_timezone.py
firebirdsql/tests/test_utils.py