Metadata-Version: 2.4
Name: firebirdsql
Version: 1.4.2
Summary: Firebird RDBMS bindings for python.
Author-email: Hajime Nakagami <nakagami@gmail.com>
Project-URL: Project, https://github.com/nakagami/pyfirebirdsql/
Keywords: Firebird
Classifier: Development Status :: 5 - Production/Stable
Classifier: Operating System :: OS Independent
Classifier: Programming Language :: Python
Classifier: Programming Language :: Python :: 3
Classifier: Topic :: Database
License-File: LICENSE
Dynamic: license-file
